sql_cable/__init__.py
sql_cable/columns.py
sql_cable/db.py
sql_cable/migrations.py
sql_cable/model.py
sql_cable/session.py
sql_cable/version.py
sql_cable/queries/__init__.py
sql_cable/queries/delete.py
sql_cable/queries/insert.py
sql_cable/queries/query_objects.py
sql_cable/queries/select.py
sql_cable/queries/update.py
sql_cable/tests/__init__.py
sql_cable/tests/delete.py
sql_cable/tests/insert.py
sql_cable/tests/make_migrations.py
sql_cable/tests/migrate.py
sql_cable/tests/req.py
sql_cable/tests/select.py
sql_cable/tests/update.py
sql_cable-1.0.1.dist-info/LICENSE
sql_cable-1.0.1.dist-info/METADATA
sql_cable-1.0.1.dist-info/WHEEL
sql_cable-1.0.1.dist-info/top_level.txt
sql_cable-1.0.1.dist-info/RECORD
